{
    "remaining_requests": 17661,
    "original_status": 200,
    "pc_status": 200,
    "url": "https://www.amazon.com/Dokotoo-Turtleneck-Sweaters-Pullovers-Outerwear/dp/B07WF3N4YC",
    "body": {
        "name": "Dokotoo Womens 2023 Winter Fall Solid Turtleneck High Neck Balloon Long Sleeve Sweaters Pullover Outerwear",
        "price": "$40.95",
        "originalPrice": "",
        "rawPrice": 40.95,
        "currency": "$",
        "canonicalUrl": "https://www.amazon.com/Dokotoo-Turtleneck-Sweaters-Pullover-Outerwear/dp/B09M7FHZ7L",
        "soldBy": null,
        "deliveredBy": "",
        "parentAsin": [
            "B09M7FHZ7L"
        ],
        "asinVariationValues": [
            {
                "asin": "B0BFXH6Y7N",
                "variationName": "Color",
                "variationValue": "A Deep Purple",
                "price": "",
                "variationImageURL": "https://m.media-amazon.com/images/I/517A7TlV6HL._SX38_SY50_CR,0,0,38,50_.jpg"
            },
            {
                "asin": "B0BFXHZVBR",
                "variationName": "Color",
                "variationValue": "A Gray 3",
                "price": "",
                "variationImageURL": "https://m.media-amazon.com/images/I/51DDWrSXqSL._SX38_SY50_CR,0,0,38,50_.jpg"
            },
            {
                "asin": "B097Q54JXQ",
                "variationName": "Color",
                "variationValue": "A Green",
                "price": "",
                "variationImageURL": "https://m.media-amazon.com/images/I/51fYEL6xIbL._SX38_SY50_CR,0,0,38,50_.jpg"
            },
            {
                "asin": "B097Q1ZY77",
                "variationName": "Color",
                "variationValue": "A Pink",
                "price": "",
                "variationImageURL": "https://m.media-amazon.com/images/I/51Lv1TR40EL._SX38_SY50_CR,0,0,38,50_.jpg"
            },
            {
                "asin": "B0BFXK43XL",
                "variationName": "Color",
                "variationValue": "A Red 2",
                "price": "",
                "variationImageURL": "https://m.media-amazon.com/images/I/510A3+ThrqL._SX38_SY50_CR,0,0,38,50_.jpg"
            },
            {
                "asin": "B0BFXHF4YZ",
                "variationName": "Color",
                "variationValue": "A White",
                "price": "",
                "variationImageURL": "https://m.media-amazon.com/images/I/41nfID-bbaL._SX38_SY50_CR,0,0,38,50_.jpg"
            },
            {
                "asin": "B07TF7W2CC",
                "variationName": "Color",
                "variationValue": "A Yellow",
                "price": "",
                "variationImageURL": "https://m.media-amazon.com/images/I/51UNbry-VvL._SX38_SY50_CR,0,0,38,50_.jpg"
            },
            {
                "asin": "B0B3XRPHMN",
                "variationName": "Color",
                "variationValue": "A1 Beige",
                "price": "",
                "variationImageURL": "https://m.media-amazon.com/images/I/51ZB5yUQxFL._SX38_SY50_CR,0,0,38,50_.jpg"
            },
            {
                "asin": "B07TF6JL5Q",
                "variationName": "Color",
                "variationValue": "A Blue",
                "price": "",
                "variationImageURL": "https://m.media-amazon.com/images/I/51qBJjv7GHL._SX38_SY50_CR,0,0,38,50_.jpg"
            },
            {
                "asin": "B07TC2PYXF",
                "variationName": "Color",
                "variationValue": "A Gray",
                "price": "",
                "variationImageURL": "https://m.media-amazon.com/images/I/51l6pnd8NWL._SX38_SY50_CR,0,0,38,50_.jpg"
            },
            {
                "asin": "B0BFXGMMZM",
                "variationName": "Color",
                "variationValue": "A Light Brown",
                "price": "",
                "variationImageURL": "https://m.media-amazon.com/images/I/51DTHCNy9rL._SX38_SY50_CR,0,0,38,50_.jpg"
            },
            {
                "asin": "B07TF7R7ZS",
                "variationName": "Color",
                "variationValue": "A Red",
                "price": "",
                "variationImageURL": "https://m.media-amazon.com/images/I/51jL3JDcUVS._SX38_SY50_CR,0,0,38,50_.jpg"
            },
            {
                "asin": "B097Q1HWQ9",
                "variationName": "Color",
                "variationValue": "A Yellow 2",
                "price": "",
                "variationImageURL": "https://m.media-amazon.com/images/I/514hSj0dlyL._SX38_SY50_CR,0,0,38,50_.jpg"
            },
            {
                "asin": "B0CG1DYSBT",
                "variationName": "Color",
                "variationValue": "A1 Green",
                "price": "",
                "variationImageURL": "https://m.media-amazon.com/images/I/514aH3qw5QL._SX38_SY50_CR,0,0,38,50_.jpg"
            },
            {
                "asin": "B0B3XQT5SX",
                "variationName": "Color",
                "variationValue": "A1 Khaki",
                "price": "",
                "variationImageURL": "https://m.media-amazon.com/images/I/51Evj2X+n2L._SX38_SY50_CR,0,0,38,50_.jpg"
            },
            {
                "asin": "B0B3XPG168",
                "variationName": "Color",
                "variationValue": "A1 Purple",
                "price": "",
                "variationImageURL": "https://m.media-amazon.com/images/I/51ALmtv1D-L._SX38_SY50_CR,0,0,38,50_.jpg"
            },
            {
                "asin": "B0B3XPFLWD",
                "variationName": "Color",
                "variationValue": "A1 Rose",
                "price": "",
                "variationImageURL": "https://m.media-amazon.com/images/I/51Ede1FxrlL._SX38_SY50_CR,0,0,38,50_.jpg"
            },
            {
                "asin": "B07YRFRFS4",
                "variationName": "Color",
                "variationValue": "A Black",
                "price": "",
                "variationImageURL": "https://m.media-amazon.com/images/I/51LC69vK2ZL._SX38_SY50_CR,0,0,38,50_.jpg"
            },
            {
                "asin": "B0BFXJGHV9",
                "variationName": "Color",
                "variationValue": "A Blue 2",
                "price": "",
                "variationImageURL": "https://m.media-amazon.com/images/I/51KIMoampHL._SX38_SY50_CR,0,0,38,50_.jpg"
            },
            {
                "asin": "B0BFXGDQD9",
                "variationName": "Color",
                "variationValue": "A Dark Red",
                "price": "",
                "variationImageURL": "https://m.media-amazon.com/images/I/51WzIMS4+PL._SX38_SY50_CR,0,0,38,50_.jpg"
            },
            {
                "asin": "B0CG1DD4D1",
                "variationName": "Color",
                "variationValue": "A Orange",
                "price": "",
                "variationImageURL": "https://m.media-amazon.com/images/I/51BPVwuNPzL._SX38_SY50_CR,0,0,38,50_.jpg"
            },
            {
                "asin": "B07Y8D2N38",
                "variationName": "Color",
                "variationValue": "B Apricot",
                "price": "",
                "variationImageURL": "https://m.media-amazon.com/images/I/51WQo2PSUAL._SX38_SY50_CR,0,0,38,50_.jpg"
            },
            {
                "asin": "B07W8C9JRW",
                "variationName": "Color",
                "variationValue": "B Beige",
                "price": "",
                "variationImageURL": "https://m.media-amazon.com/images/I/41Y685fl5kL._SX38_SY50_CR,0,0,38,50_.jpg"
            },
            {
                "asin": "B07Y8DLXBW",
                "variationName": "Color",
                "variationValue": "B Black",
                "price": "",
                "variationImageURL": "https://m.media-amazon.com/images/I/41DcOzV3DgL._SX38_SY50_CR,0,0,38,50_.jpg"
            },
            {
                "asin": "B0B3XRP2PT",
                "variationName": "Color",
                "variationValue": "B Blue 2",
                "price": "",
                "variationImageURL": "https://m.media-amazon.com/images/I/412I0r7FpkL._SX38_SY50_CR,0,0,38,50_.jpg"
            },
            {
                "asin": "B07WLSC4QN",
                "variationName": "Color",
                "variationValue": "B Gray",
                "price": "",
                "variationImageURL": "https://m.media-amazon.com/images/I/51sY5+0l75L._SX38_SY50_CR,0,0,38,50_.jpg"
            },
            {
                "asin": "B07Y8DM687",
                "variationName": "Color",
                "variationValue": "B Green",
                "price": "",
                "variationImageURL": "https://m.media-amazon.com/images/I/41WSuxoDB1L._SX38_SY50_CR,0,0,38,50_.jpg"
            },
            {
                "asin": "B07WLPRWKD",
                "variationName": "Color",
                "variationValue": "B Khaki",
                "price": "",
                "variationImageURL": "https://m.media-amazon.com/images/I/51nB8pgKsGL._SX38_SY50_CR,0,0,38,50_.jpg"
            },
            {
                "asin": "B07W8CB1F3",
                "variationName": "Color",
                "variationValue": "B Orange",
                "price": "",
                "variationImageURL": "https://m.media-amazon.com/images/I/51IVzkEudhL._SX38_SY50_CR,0,0,38,50_.jpg"
            },
            {
                "asin": "B097PNDRZM",
                "variationName": "Color",
                "variationValue": "C Blue 5",
                "price": "",
                "variationImageURL": "https://m.media-amazon.com/images/I/51iRm7zDUlL._SX38_SY50_CR,0,0,38,50_.jpg"
            },
            {
                "asin": "B097PNBRKS",
                "variationName": "Color",
                "variationValue": "C Brown",
                "price": "",
                "variationImageURL": "https://m.media-amazon.com/images/I/51lEnh3E4NL._SX38_SY50_CR,0,0,38,50_.jpg"
            },
            {
                "asin": "B07YKS747B",
                "variationName": "Color",
                "variationValue": "C Multicoloured 22",
                "price": "",
                "variationImageURL": "https://m.media-amazon.com/images/I/51S1t5PQnvL._SX38_SY50_CR,0,0,38,50_.jpg"
            },
            {
                "asin": "B0CG1DPPG4",
                "variationName": "Color",
                "variationValue": "A Gray 2",
                "price": "",
                "variationImageURL": "https://m.media-amazon.com/images/I/51jvb9dTh9L._SX38_SY50_CR,0,0,38,50_.jpg"
            },
            {
                "asin": "B0BFXHJWS6",
                "variationName": "Color",
                "variationValue": "A Purple",
                "price": "",
                "variationImageURL": "https://m.media-amazon.com/images/I/51IKnKUDgVL._SX38_SY50_CR,0,0,38,50_.jpg"
            },
            {
                "asin": "B0CG1D8VSL",
                "variationName": "Color",
                "variationValue": "A1 Sky Blue",
                "price": "",
                "variationImageURL": "https://m.media-amazon.com/images/I/51AclCUInAL._SX38_SY50_CR,0,0,38,50_.jpg"
            },
            {
                "asin": "B0B3XS9GD4",
                "variationName": "Color",
                "variationValue": "B Pink",
                "price": "",
                "variationImageURL": "https://m.media-amazon.com/images/I/513hs9egCLL._SX38_SY50_CR,0,0,38,50_.jpg"
            },
            {
                "asin": "B0CG1CLW74",
                "variationName": "Color",
                "variationValue": "A Deep Blue",
                "price": "",
                "variationImageURL": "https://m.media-amazon.com/images/I/51c5nKYeHzL._SX38_SY50_CR,0,0,38,50_.jpg"
            },
            {
                "asin": "B0CG1FPGMM",
                "variationName": "Color",
                "variationValue": "A Khaki",
                "price": "",
                "variationImageURL": "https://m.media-amazon.com/images/I/51Hv0grEu3L._SX38_SY50_CR,0,0,38,50_.jpg"
            },
            {
                "asin": "B0BFXKW9RG",
                "variationName": "Color",
                "variationValue": "A Pink 2",
                "price": "",
                "variationImageURL": "https://m.media-amazon.com/images/I/51Py9KDE8tL._SX38_SY50_CR,0,0,38,50_.jpg"
            },
            {
                "asin": "B0CG1CR3V9",
                "variationName": "Color",
                "variationValue": "B Purple",
                "price": "",
                "variationImageURL": "https://m.media-amazon.com/images/I/51CIMTHcPwL._SX38_SY50_CR,0,0,38,50_.jpg"
            },
            {
                "asin": "B07YKPG586",
                "variationName": "Color",
                "variationValue": "C White 1",
                "price": "",
                "variationImageURL": "https://m.media-amazon.com/images/I/51kf-sYBw8L._SX38_SY50_CR,0,0,38,50_.jpg"
            },
            {
                "asin": "B0BFXGRQ39",
                "variationName": "Color",
                "variationValue": "A Mint Green",
                "price": "",
                "variationImageURL": "https://m.media-amazon.com/images/I/51KfMN2NrRL._SX38_SY50_CR,0,0,38,50_.jpg"
            },
            {
                "asin": "B0BFXH62NV",
                "variationName": "Color",
                "variationValue": "A Turquoise Green",
                "price": "",
                "variationImageURL": "https://m.media-amazon.com/images/I/51xjgJr-LpL._SX38_SY50_CR,0,0,38,50_.jpg"
            },
            {
                "asin": "B0B3XN5K4J",
                "variationName": "Color",
                "variationValue": "C Brown 01",
                "price": "",
                "variationImageURL": "https://m.media-amazon.com/images/I/51lEnh3E4NL._SX38_SY50_CR,0,0,38,50_.jpg"
            },
            {
                "asin": "B0BFXFPXKX",
                "variationName": "Size",
                "variationValue": "X-Small",
                "variationImageURL": null
            },
            {
                "asin": "B07W8C9JRW",
                "variationName": "Size",
                "variationValue": "Small",
                "variationImageURL": null
            },
            {
                "asin": "B07W77Z6XX",
                "variationName": "Size",
                "variationValue": "Medium",
                "variationImageURL": null
            },
            {
                "asin": "B07WF3N4YC",
                "variationName": "Size",
                "variationValue": "Large",
                "variationImageURL": null
            },
            {
                "asin": "B097PP6PG8",
                "variationName": "Size",
                "variationValue": "X-Large",
                "variationImageURL": null
            },
            {
                "asin": "B0BFXFM2K2",
                "variationName": "Size",
                "variationValue": "XX-Large",
                "variationImageURL": null
            }
        ],
        "isPrime": true,
        "inStock": false,
        "maximumQuantity": "",
        "stockDetail": "",
        "couponInfo": "",
        "mainImage": "https://images-na.ssl-images-amazon.com/images/I/41Y685fl5kL.jpg",
        "images": [
            "https://images-na.ssl-images-amazon.com/images/I/51-k3oItEVS.jpg",
            "https://images-na.ssl-images-amazon.com/images/I/414PO4Z4e0S.jpg",
            "https://images-na.ssl-images-amazon.com/images/I/51n3SfS6lvL.jpg",
            "https://images-na.ssl-images-amazon.com/images/I/61z56XcpcgL.jpg",
            "https://images-na.ssl-images-amazon.com/images/I/51xsklH17WL.jpg",
            "https://images-na.ssl-images-amazon.com/images/I/51bgQpTMrjL.jpg"
        ],
        "imagesCount": 7,
        "highResolutionImages": [],
        "videos": [
            "https://m.media-amazon.com/images/S/vse-vms-transcoding-artifact-us-east-1-prod/b189954d-f4a3-4212-86a9-0860a813c93f/default.jobtemplate.mp4.480.mp4",
            "https://m.media-amazon.com/images/S/vse-vms-transcoding-artifact-us-east-1-prod/a2417138-428a-44e2-9e5b-c1b2f56bc772/default.jobtemplate.mp4.480.mp4"
        ],
        "videosCount": 2,
        "productGuidesAndDocuments": {
            "productDocumentationLink": "",
            "userManualLink": ""
        },
        "byLineInfo": {
            "name": "Visit the Dokotoo Store",
            "link": "https://www.amazon.com/stores/Dokotoo/page/F1F283FF-D7A3-431C-8FA3-84D3B81094F5?ref_=ast_bln"
        },
        "brand": "Dokotoo",
        "merchantInfo": "",
        "customerReview": "4.3 out of 5 stars",
        "customerReviewCount": 7871,
        "answeredQuestionsCount": 0,
        "editorialReviews": [],
        "warrantyMessage": "",
        "shippingMessage": "",
        "deliveryMessages": [],
        "climatePledgeFriendly": {
            "present": false,
            "details": ""
        },
        "features": [
            "Fabric type 60% Cotton, 40% Acrylic",
            "Care instructions Line dry",
            "Origin Package Contents: 1 X Piece Sweater",
            "Closure type Pull On",
            "Embrace chilly days in this chunky cable-knit sweaters pullovers that will no doubt keep you warm with its turtleneck and relaxed silhouette. A bold cable knit amplifies the vintage attitude of this slouchy, casual-chic sweater.",
            "Thick fabric, oversized sweaters outerwear fit great for fall and winter.Get cozy in this chunky cable-knit oversized pullover designed in a slouchy, cropped fit with a sinuous ribbed hem. Its ready to wear style makes it a fantastic piece to wear all year round with all your seasonal styles",
            "This beautiful thick and chunky Turtleneck Sweater features the popular Cable knitted. The sweater jumper features an oversized collar for a dramatic yet cozy style. Taking inspiration from the typical chunkyknit sweater, this is the perfect garment to keep you warm and stylish this season.",
            "Loose Fit/Turtleneck/Cable Knit/Batwing Sleeve/Raglan Long Sleeve/No Pockets/Not Lined/Soft & Stretchy/Lightweight Fabrication/Solid/Winter/Autumn/Sport/Casual/Elegant/Basic Sweaters Pullovers Outerwear for You.",
            "Wash Recommended With Cold Water/Do Not Bleach/Hang Or Line Dry/Wash with like colours,that will increase the durability of your clothes."
        ],
        "description": "",
        "breadCrumbs": [
            {
                "name": "Clothing, Shoes & Jewelry",
                "link": "https://www.amazon.com/amazon-fashion/b/ref=dp_bc_aui_C_1?ie=UTF8&node=7141123011"
            },
            {
                "name": "Women",
                "link": "https://www.amazon.com/Womens-Fashion/b/ref=dp_bc_aui_C_2?ie=UTF8&node=7147440011"
            },
            {
                "name": "Clothing",
                "link": "https://www.amazon.com/Womens-Clothing/b/ref=dp_bc_aui_C_3?ie=UTF8&node=1040660"
            },
            {
                "name": "Sweaters",
                "link": "https://www.amazon.com/Womens-Sweaters/b/ref=dp_bc_aui_C_4?ie=UTF8&node=1044456"
            },
            {
                "name": "Pullovers",
                "link": "https://www.amazon.com/Womens-Pullover-Sweaters/b/ref=dp_bc_aui_C_5?ie=UTF8&node=2368384011"
            }
        ],
        "productInformation": [
            {
                "name": "Package Dimensions \u200f",
                "value": "\u200e 15 x 12.5 x 2 inches; 1.1 Pounds"
            },
            {
                "name": "Item model number \u200f",
                "value": "\u200e WG5W270034-108-XS"
            },
            {
                "name": "Department \u200f",
                "value": "\u200e womens"
            },
            {
                "name": "Date First Available \u200f",
                "value": "\u200e September 20, 2022"
            },
            {
                "name": "ASIN \u200f",
                "value": "\u200e B0BFXFPXKX"
            },
            {
                "name": "Best Sellers Rank",
                "value": "#9,426 in Clothing, Shoes & Jewelry (See Top 100 in Clothing, Shoes & Jewelry) #80 in Women's Pullover Sweaters"
            },
            {
                "name": "Customer Reviews",
                "value": "4.3 4.3 out of 5 stars 7,871 ratings"
            }
        ],
        "manufacturerProductDescription": [
            {
                "media_text": "Previous page Next page",
                "media_link": []
            },
            {
                "media_text": "DOKOTOO SWEATER Love Fashion, Love Beauty, Love DOKOTOO. Item\uff1aSweater Sleeve\uff1aLong sleeve Pattern\uff1aSolid color",
                "media_link": []
            },
            {
                "media_text": "Front show Makes you look fashionable, perfect wear with jeans, joggers, leggings and dress Neckline The pullover sweater with batwing long sleeve and tuetleneck design Material Smooth and soft, comfortable fabric Hem Chunky chic, the detail and fit are so perfect for styling",
                "media_link": [
                    "https://m.media-amazon.com/images/S/aplus-media-library-service-media/92818941-f735-4a47-8d11-d5c86c73fe4b.__CR0,0,300,225_PT0_SX300_V1___.jpg",
                    "https://m.media-amazon.com/images/S/aplus-media-library-service-media/88f1062a-c981-48da-bcdd-d9c7030d9fde.__CR0,0,300,225_PT0_SX300_V1___.jpg",
                    "https://m.media-amazon.com/images/S/aplus-media-library-service-media/bafb8d0b-c4d1-4ec7-b002-5abf39683d45.__CR0,0,300,225_PT0_SX300_V1___.jpg",
                    "https://m.media-amazon.com/images/S/aplus-media-library-service-media/d47926ff-722e-4392-8195-344a8f9693a8.__CR0,0,300,225_PT0_SX300_V1___.jpg"
                ]
            },
            {
                "media_text": "DOKOTOO SWEATER COLLECTION Chunky High Neck Sweater Add to Cart Cable Knit Sweater Add to Cart Turtle Neck Sweater Add to Cart V Neck Wrap Sweaters See Details Lantarn Sleeve Sweater Add to Cart 3/4 Sleeve Sweater Add to Cart Short Sleeve Sweater Add to Cart Customer Reviews 4.3 out of 5 stars 7,871 4.3 out of 5 stars 1,734 4.2 out of 5 stars 2,307 3.5 out of 5 stars 666 4.0 out of 5 stars 2,673 4.2 out of 5 stars 2,307 4.1 out of 5 stars 53 Price $42.88$42.88 $41.88$41.88 $35.98$35.98 \u2014 $29.73$29.73 $35.98$35.98 $24.99$24.99 Pattern Solid Color Solid Color Solid Color Solid Color Solid Color Stripe Color Block Material 60%Cotton+40%Acrylic 100%Acrylic 60% Cotton+40% Acrylic 100% Cotton 100%Acrylic 100%Acrylic 60%Cotton+40%Acrylic Feature Cable Knit Cable Knit Cable Knit Wrap Hollow Out 3/4 Sleeve Hollow Out Neckline Turtleneck Turtleneck Turtleneck V Neck Crewneck Crewneck Crewneck Brand Dokotoo Dokotoo Dokotoo Dokotoo Dokotoo Dokotoo Dokotoo",
                "media_link": []
            },
            {
                "media_text": "DOKOTOO SWEATER COLLECTION Loose Sweater See Details Hollow Out Sweaters See Details Casual Loose Sweaters Add to Cart Fashion Winter Sweater Add to Cart Stripe V Neck Sweater Add to Cart Off Shoulder Sweater Add to Cart Casual Loose Sweaters Add to Cart Customer Reviews 4.5 out of 5 stars 8 3.9 out of 5 stars 388 4.0 out of 5 stars 2,673 4.2 out of 5 stars 1,454 4.2 out of 5 stars 2,307 4.4 out of 5 stars 2,180 4.0 out of 5 stars 2,673 Price \u2014 \u2014 $32.29$32.29 $38.99$38.99 $35.98$35.98 $39.89$39.89 $32.29$32.29 Pattern Solid Color Solid Color Color Block Solid Color Stripe Solid Color Color Block Material 55%Acrylic+45%Cotton 100% Acrylic 100%Acrylic 100%Polyester 100%Acrylic 55%Acrylic+45%Cotton 100%Acrylic Feature Knitted Hollow Out Hollow Out Waffle Knit Off Shoulder Off Shoulder Hollow Out Neckline Turtleneck Crew Neck V Neck V Neck V Neck Crew Neck V Neck Brand Dokotoo Dokotoo Dokotoo Dokotoo Dokotoo Dokotoo Dokotoo",
                "media_link": []
            }
        ],
        "manufacturerProductImages": [
            "https://m.media-amazon.com/images/S/aplus-media-library-service-media/5b51d058-d995-436e-b8e1-df158404a4c7.__CR0,0,1464,600_PT0_SX1464_V1___.jpg",
            "https://m.media-amazon.com/images/S/aplus-media-library-service-media/d30a2529-30af-4e7a-89d1-917fd6f0326f.__CR0,0,1464,600_PT0_SX1464_V1___.jpg",
            "https://m.media-amazon.com/images/S/aplus-media-library-service-media/305129cc-11d2-47d7-9e25-448e98f08ef5.__CR0,0,1464,600_PT0_SX1464_V1___.jpg",
            "https://m.media-amazon.com/images/S/aplus-media-library-service-media/29e961e2-b4c9-4c18-b6f9-b9e0c524e706.__CR0,0,1464,600_PT0_SX1464_V1___.jpg",
            "https://m.media-amazon.com/images/S/aplus-media-library-service-media/b75fdc13-c401-4b9c-8a30-6a2d2d1efa35.__CR0,0,1464,600_PT0_SX1464_V1___.jpg",
            "https://m.media-amazon.com/images/S/aplus-media-library-service-media/5ca5bd2e-5605-4f48-b07d-d8fcb31588ac.__CR0,0,1464,600_PT0_SX1464_V1___.jpg",
            "https://m.media-amazon.com/images/S/aplus-media-library-service-media/60fc203d-8422-4dc1-bb01-4a6980ffa5ee.__CR0,0,1464,600_PT0_SX1464_V1___.jpg",
            "https://m.media-amazon.com/images/S/aplus-media-library-service-media/92818941-f735-4a47-8d11-d5c86c73fe4b.__CR0,0,300,225_PT0_SX300_V1___.jpg",
            "https://m.media-amazon.com/images/S/aplus-media-library-service-media/88f1062a-c981-48da-bcdd-d9c7030d9fde.__CR0,0,300,225_PT0_SX300_V1___.jpg",
            "https://m.media-amazon.com/images/S/aplus-media-library-service-media/bafb8d0b-c4d1-4ec7-b002-5abf39683d45.__CR0,0,300,225_PT0_SX300_V1___.jpg",
            "https://m.media-amazon.com/images/S/aplus-media-library-service-media/d47926ff-722e-4392-8195-344a8f9693a8.__CR0,0,300,225_PT0_SX300_V1___.jpg",
            "https://m.media-amazon.com/images/S/aplus-media-library-service-media/fce97978-adae-4674-8c06-82de29ef9566.__CR0,0,1464,600_PT0_SX1464_V1___.jpg",
            "https://m.media-amazon.com/images/S/aplus-media-library-service-media/e18176ca-8606-49f7-b665-b090d837f287.__CR0,0,200,225_PT0_SX200_V1___.jpg",
            "https://m.media-amazon.com/images/S/aplus-media-library-service-media/05ad8a1b-4b5e-4a9d-a1f7-185a1618a535.__CR0,0,200,225_PT0_SX200_V1___.jpg",
            "https://m.media-amazon.com/images/S/aplus-media-library-service-media/155e6be0-ea33-472c-b7c0-cb6e55cb41e0.__CR0,0,200,225_PT0_SX200_V1___.jpg",
            "https://m.media-amazon.com/images/S/aplus-media-library-service-media/e16e1f02-cd72-41f6-b79b-7d6c3acace8f.__CR0,0,200,225_PT0_SX200_V1___.jpg",
            "https://m.media-amazon.com/images/S/aplus-media-library-service-media/8560f59b-8e43-44c6-a9a6-5cb501595264.__CR0,0,200,225_PT0_SX200_V1___.jpg",
            "https://m.media-amazon.com/images/S/aplus-media-library-service-media/5ea18fb9-b845-4f1f-9280-0f54e002e69d.__CR0,0,200,225_PT0_SX200_V1___.jpg",
            "https://m.media-amazon.com/images/S/aplus-media-library-service-media/b448fae1-ffbe-4ced-b69c-078675f4bd79.__CR0,0,200,225_PT0_SX200_V1___.jpg",
            "https://m.media-amazon.com/images/S/aplus-media-library-service-media/28cc17f8-9290-408b-9863-502a070ecb19.__CR0,0,200,225_PT0_SX200_V1___.jpg",
            "https://m.media-amazon.com/images/S/aplus-media-library-service-media/e31380a6-1328-4fe1-9ab5-8df093bb1d41.__CR0,0,200,225_PT0_SX200_V1___.jpg",
            "https://m.media-amazon.com/images/S/aplus-media-library-service-media/203010d6-3cab-49ca-9714-73f89cf591ce.__CR0,0,200,225_PT0_SX200_V1___.jpg",
            "https://m.media-amazon.com/images/S/aplus-media-library-service-media/fa64181d-17c6-4d4b-899d-5faafecd1ba7.__CR0,0,200,225_PT0_SX200_V1___.jpg",
            "https://m.media-amazon.com/images/S/aplus-media-library-service-media/f1ff5712-24ff-43b7-82c8-868cd5cb100b.__CR0,0,200,225_PT0_SX200_V1___.jpg",
            "https://m.media-amazon.com/images/S/aplus-media-library-service-media/aa6272cc-6aec-414a-9b31-f1be8034c0bf.__CR0,0,200,225_PT0_SX200_V1___.jpg"
        ],
        "sponsoredAds": [],
        "productReviewBottom": [],
        "reviews": [
            {
                "reviewerName": "Joyful Living",
                "reviewerLink": "https://www.amazon.com/gp/profile/amzn1.account.AE7U5GXFMYFLQ7SRIULJYIQBFY6Q",
                "reviewLink": "https://www.amazon.com/gp/customer-reviews/R28RK1KWENZDMS?ASIN=B09M7FHZ7L",
                "reviewRating": "5.0 out of 5 stars",
                "reviewDate": "Reviewed in the United States on January 13, 2024",
                "reviewTitle": "5.0 out of 5 stars Absolutely Gorgeous Sweater",
                "reviewText": "Cotton/acrylic combination (as far as I can tell) that is super soft and beautiful. The actual color is winter white rather than a stark white. It matches all my winter white corduroy pants! The tirtleneck collar is thick, luxurious, and generous. The sleeves are not as generous (they don't droop much) as they appear in the photograph, which I would prefer, but I love this sweater anyway -- and ordered a second one in winter white. All in all, quite stunning!The so-called purple color is actually a lilac/violet color that is lovely. I ordered a second one because my husband really likes the color.The yellow gold color is gorgeous and very saturated, if you love that color. I do. It's happy and matches one of my jackets perfectly. It is more gold than yellow.After seeing how great these sweaters are, I ordered several more colors. Gray is a challenging color to match. I am thrilled to say that this silver gray blends beautifully with the darker silver gray corduroy pants that I have. Worn with my sterling silver beads, this will be a gorgeous outfit.I am wearing this sweater in royal blue today with the coffee brown corduroy pants. When I walked out of my dressing area, my husband said, \"Wow! You look great. I really like that sweater.\" Now that is great feedback!",
                "reviewVotes": "8 people found this helpful",
                "reviewVerifiedPurchase": true,
                "reviewCommentCount": 0,
                "media": {
                    "images": [],
                    "video": ""
                }
            },
            {
                "reviewerName": "Nat",
                "reviewerLink": "https://www.amazon.com/gp/profile/amzn1.account.AH7I7PZU7ZN6XCV6MA6WIR6BJBEA",
                "reviewLink": "https://www.amazon.com/gp/customer-reviews/R2HP9F909GBQVI?ASIN=B09M7FHZ7L",
                "reviewRating": "2.0 out of 5 stars",
                "reviewDate": "Reviewed in the United States on December 16, 2022",
                "reviewTitle": "2.0 out of 5 stars Color not as pictured",
                "reviewText": "I loved the burnt orange color in pics & ordered it. It is not burnt orange, at all. It\u2019s a bright orange",
                "reviewVotes": "14 people found this helpful",
                "reviewVerifiedPurchase": true,
                "reviewCommentCount": 0,
                "media": {
                    "images": [],
                    "video": ""
                }
            },
            {
                "reviewerName": "Laurie Ann Potter",
                "reviewerLink": "https://www.amazon.com/gp/profile/amzn1.account.AET2YUYQG6QSKVZKOBDYJPJNM2WQ",
                "reviewLink": "https://www.amazon.com/gp/customer-reviews/R8CJE0WLGT0SI?ASIN=B09M7FHZ7L",
                "reviewRating": "5.0 out of 5 stars",
                "reviewDate": "Reviewed in the United States on February 3, 2024",
                "reviewTitle": "5.0 out of 5 stars Beautiful sweater!",
                "reviewText": "These are the most amazing sweaters. I am 5\u20198\u201d, 195 lb, hot natured, and pear shaped. These fit perfectly for pear shaped women, which most of us are. I ordered xl and got several colors. I wash them in cold and dry them inside out the first time I wash them in the dryer on medium. Some colors have been a little longer than others , and for those I leave them in the dryer a little longer. That one dryer event shrank them just a bit and now they hit just at my lower waist. Perfect. If you do this you might want to pull them out a few times in the drying cycle to make sure they don\u2019t shrink too much for you. I do air dry then after that one time in the dryer. The collar is not tight at all . The sweater is not scratchy at all . As I said , I\u2019m hot natured but these are just enough of an open weave that air passes through \u2026. Not enough that the sweater is see through though. I highly recommend !",
                "reviewVotes": "One person found this helpful",
                "reviewVerifiedPurchase": true,
                "reviewCommentCount": 0,
                "media": {
                    "images": [],
                    "video": ""
                }
            },
            {
                "reviewerName": "C Simmons",
                "reviewerLink": "https://www.amazon.com/gp/profile/amzn1.account.AEGB4J2Y732JVODH2IRNEFBLMIMA",
                "reviewLink": "https://www.amazon.com/gp/customer-reviews/R2PVL2NEQTD1CS?ASIN=B09M7FHZ7L",
                "reviewRating": "4.0 out of 5 stars",
                "reviewDate": "Reviewed in the United States on January 16, 2024",
                "reviewTitle": "4.0 out of 5 stars Soft and roomy",
                "reviewText": "Great color. It's really soft and roomy. Wasn't to long,just enough length. Stitching was tight and well done. Overall it was a good buy for me.",
                "reviewVotes": "2 people found this helpful",
                "reviewVerifiedPurchase": true,
                "reviewCommentCount": 0,
                "media": {
                    "images": [],
                    "video": ""
                }
            },
            {
                "reviewerName": "thecrow601",
                "reviewerLink": "https://www.amazon.com/gp/profile/amzn1.account.AEK5F4OE4KNWSDRO6I7BA3TTSNSQ",
                "reviewLink": "https://www.amazon.com/gp/customer-reviews/RG8D7M5UO4VCM?ASIN=B09M7FHZ7L",
                "reviewRating": "5.0 out of 5 stars",
                "reviewDate": "Reviewed in the United States on January 19, 2024",
                "reviewTitle": "5.0 out of 5 stars Great Oversized Sweater",
                "reviewText": "I purchased the black sweater in size Medium (as per the recommendation of Amazon because I typically would order a Small). I'm 5'8\" and 135 lbs. This definitely fits oversized as the sleeves are very long but looks on me like the picture. As other reviews have stated, though, it is knitted loosely so it's not super warm and I'll wear a tank top underneath. It's VERY soft and I love the oversized look with jeans.",
                "reviewVotes": "2 people found this helpful",
                "reviewVerifiedPurchase": true,
                "reviewCommentCount": 0,
                "media": {
                    "images": [],
                    "video": ""
                }
            },
            {
                "reviewerName": "Birdie",
                "reviewerLink": "https://www.amazon.com/gp/profile/amzn1.account.AFPMQFX6FRFNXEYXQJJXUI7AF6JA",
                "reviewLink": "https://www.amazon.com/gp/customer-reviews/RLSRQKOOU7T7A?ASIN=B09M7FHZ7L",
                "reviewRating": "5.0 out of 5 stars",
                "reviewDate": "Reviewed in the United States on January 8, 2024",
                "reviewTitle": "5.0 out of 5 stars Great sweater watch the colors",
                "reviewText": "I bought two of these, first the apricot. I thought it might be a blush of an orange. It was more like a yellow mixed with blue if you know the color wheel. It wasn\u2019t an earthy color I couldn\u2019t get it to match any scarves I had so I gave up and bought this and gave up. I\u2019ve had good luck with mustard yellows and cinnamon hoodies when looking for colors instead of rubber ducky yellows and road construction orange but I\u2019ve found it best to read reviews what people said about the colors. So,this was great but don\u2019t gamble on the apricot.",
                "reviewVotes": "2 people found this helpful",
                "reviewVerifiedPurchase": true,
                "reviewCommentCount": 0,
                "media": {
                    "images": [],
                    "video": ""
                }
            },
            {
                "reviewerName": "KyleeKylee",
                "reviewerLink": "https://www.amazon.com/gp/profile/amzn1.account.AFP6WZFZ4BCSMMVLHNJ2X435Y7OA",
                "reviewLink": "https://www.amazon.com/gp/customer-reviews/RDDYSHHPG5V8X?ASIN=B09M7FHZ7L",
                "reviewRating": "3.0 out of 5 stars",
                "reviewDate": "Reviewed in the United States on November 26, 2022",
                "reviewTitle": "3.0 out of 5 stars Very cute and comfy, but PLEASE WASH A COUPLE TIMES BEFORE WEARING",
                "reviewText": "This sweater is very cute and very comfortable, not itchy at all\u2026 BUT don\u2019t let that fool you. I loved the fit and look of the sweater which is why I am not giving a worse review but, if you have sensitive skin please wash a couple times before wearing and/or wear a full shirt underneath. I wore this for a couple hours and broke out on hives all over my arms, back, neck, and especially my chest. The picture attached is my chest after a couple of days, still itchy and breaking out even after a few days. I washed the sweater before wearing, but did not wear a shirt underneath because the sweater is quite warm. Im hoping if I wash it bunch of times it will be better, but I\u2019m definitely nervous to wear again because the hives are no joke! The sweater did have a very strong smell when I received it so maybe only washing it once did not get the fragrance out enough. With that being said, I don\u2019t know if it was the fragrance or fibers that caused the hives. But, the sweater is not itchy so I feel like it has to be something with the smell of the shirt. I do have sensitive skin but I never break out from clothes. I also know it was the sweater and not something else because I only have hives on the places where the sweater was directly touching my skin.",
                "reviewVotes": "218 people found this helpful",
                "reviewVerifiedPurchase": true,
                "reviewCommentCount": 0,
                "media": {
                    "images": [
                        "https://images-na.ssl-images-amazon.com/images/G/01/x-locale/common/grey-pixel.gif.jpg",
                        "https://m.media-amazon.com/images/I/71DEWiRAuYL.jpg"
                    ],
                    "video": ""
                }
            },
            {
                "reviewerName": "Amazon Customer",
                "reviewerLink": "https://www.amazon.com/gp/profile/amzn1.account.AHABLJPZHTXGO7ULYH6CO452XC4Q",
                "reviewLink": "https://www.amazon.com/gp/customer-reviews/R2ISBR43NWCAWV?ASIN=B09M7FHZ7L",
                "reviewRating": "5.0 out of 5 stars",
                "reviewDate": "Reviewed in the United States on January 28, 2024",
                "reviewTitle": "5.0 out of 5 stars Great sweater",
                "reviewText": "Quality fabric. Good fit. Washes well and holds its shape",
                "reviewVotes": "One person found this helpful",
                "reviewVerifiedPurchase": true,
                "reviewCommentCount": 0,
                "media": {
                    "images": [],
                    "video": ""
                }
            },
            {
                "reviewerName": "TrueCustomer",
                "reviewerLink": "",
                "reviewLink": "",
                "reviewRating": "5.0 out of 5 stars",
                "reviewDate": "Reviewed in Canada on January 18, 2024",
                "reviewTitle": "Buy a size larger and rock it baggy",
                "reviewText": "I love this winter sweater. It is made well and looks fashionable. I bought a size larger than I normally would so that it would fit longer and looser.",
                "reviewVotes": "",
                "reviewVerifiedPurchase": true,
                "reviewCommentCount": 0,
                "media": {
                    "images": [],
                    "video": ""
                }
            },
            {
                "reviewerName": "Rosie Ferries",
                "reviewerLink": "",
                "reviewLink": "",
                "reviewRating": "1.0 out of 5 stars",
                "reviewDate": "Reviewed in Canada on January 2, 2021",
                "reviewTitle": "Smells like chemicals / feels scratchy",
                "reviewText": "Shorter than expected. Smells strongly of plastic/chemicals, even after washing. Scratchy texture. Would not recommend.",
                "reviewVotes": "",
                "reviewVerifiedPurchase": true,
                "reviewCommentCount": 0,
                "media": {
                    "images": [],
                    "video": ""
                }
            },
            {
                "reviewerName": "Kelly Webber",
                "reviewerLink": "",
                "reviewLink": "",
                "reviewRating": "5.0 out of 5 stars",
                "reviewDate": "Reviewed in Canada on February 4, 2024",
                "reviewTitle": "Great Turtle Neck Sweater",
                "reviewText": "This sweater fits so nicely, great quality and fit!",
                "reviewVotes": "",
                "reviewVerifiedPurchase": true,
                "reviewCommentCount": 0,
                "media": {
                    "images": [],
                    "video": ""
                }
            },
            {
                "reviewerName": "Debra",
                "reviewerLink": "",
                "reviewLink": "",
                "reviewRating": "4.0 out of 5 stars",
                "reviewDate": "Reviewed in Canada on November 10, 2023",
                "reviewTitle": "Too short",
                "reviewText": "Unfortunately it's very short and had a few snags in it. Other than that it is a beautiful, warm sweater. I just wish it was a little longer.",
                "reviewVotes": "One person found this helpful",
                "reviewVerifiedPurchase": true,
                "reviewCommentCount": 0,
                "media": {
                    "images": [],
                    "video": ""
                }
            },
            {
                "reviewerName": "Julie Mascarin",
                "reviewerLink": "",
                "reviewLink": "",
                "reviewRating": "5.0 out of 5 stars",
                "reviewDate": "Reviewed in Canada on January 16, 2024",
                "reviewTitle": "Beautiful colour",
                "reviewText": "This sweater is VERY warm with a lovely colour of blue. I would suggest getting a size down from your original size as I found the sleeve part of it very long and wide especially at the wrist. Saying that, I do recommend this sweater especially if you want warmth. I received many compliments on the colour and thought the price was not bad.",
                "reviewVotes": "",
                "reviewVerifiedPurchase": true,
                "reviewCommentCount": 0,
                "media": {
                    "images": [],
                    "video": ""
                }
            }
        ],
        "otherSellers": []
    }
}